topsis/__init__.py
topsis/topsis.py
Topsis_Maanya_102003366-1.0.4.dist-info/License.txt
Topsis_Maanya_102003366-1.0.4.dist-info/METADATA
Topsis_Maanya_102003366-1.0.4.dist-info/WHEEL
Topsis_Maanya_102003366-1.0.4.dist-info/entry_points.txt
Topsis_Maanya_102003366-1.0.4.dist-info/top_level.txt
Topsis_Maanya_102003366-1.0.4.dist-info/RECORD
