Metadata-Version: 2.1
Name: Topsis-Maanya-102003366
Version: 1.0.4
Summary: Calculates Topsis Score and Rank them accordingly
Home-page: UNKNOWN
Author: Maanya Jain
Author-email: maanya.jain123@gmail.com
License: MIT
Platform: UNKNOWN
Classifier: Programming Language :: Python :: 3
Classifier: License :: OSI Approved :: MIT License
Classifier: Operating System :: OS Independent
License-File: License.txt
Requires-Dist: pandas
